fits_reader/__init__.py
fits_reader/fits_reader.py
fengreader-0.1.0.dist-info/LICENSE
fengreader-0.1.0.dist-info/METADATA
fengreader-0.1.0.dist-info/WHEEL
fengreader-0.1.0.dist-info/top_level.txt
fengreader-0.1.0.dist-info/RECORD
