Metadata-Version: 2.1
Name: fengreader
Version: 0.1.0
Summary: A simple FITS file reader
Author-email: fengpeng <765915617@qq.com>
Classifier: Programming Language :: Python :: 3
Classifier: License :: OSI Approved :: MIT License
Classifier: Operating System :: OS Independent
License-File: LICENSE
Requires-Dist: astropy
